<rune>
	<id value="32"/>
	<name display="Rune of Level Earth" id="flatten"/>
	<author>billythegoat101</author>
	<solid value="false"/>
	<sacrifices>
		Sacrifice:
		-Plant Dust: 5XP + 5xIronOre
		-Gunpowder Dust: 6XP + 5xIronOre
		-Lapis Dust: 7XP + 5xIronOre
		-Blaze Dust: 8XP + 5xIronOre
	</sacrifices>
	<description>
		Description:
		Flattens the terrain around it.
	</description>
	<design width="20" height="20" ox="0" oy="0" cx="8" cy="8">
		0,		0,		0,		0,		0,		0,		0,		0,		200,	0,		0,		200,	0,		0,		0,		0,		0,		0,		0,		0
		0,		0,		0,		0,		0,		0,		0,		0,		200,	200,	200,	200,	0,		0,		0,		0,		0,		0,		0,		0
		0,		0,		0,		0,		0,		0,		0,		0,		200,	0,		0,		200,	0,		0,		0,		0,		0,		0,		0,		0
		0,		0,		0,		0,		0,		0,		0,		0,		200,	200,	200,	200,	0,		0,		0,		0,		0,		0,		0,		0
		0,		0,		0,		0,		0,		0,		0,		0,		200,	0,		0,		200,	0,		0,		0,		0,		0,		0,		0,		0
		0,		0,		0,		0,		0,		0,		100,	100,	200,	200,	200,	200,	100,	100,	0,		0,		0,		0,		0,		0
		0,		0,		0,		0,		0,		100,	100,	300,	200,	0,		0,		200,	300,	100,	100,	0,		0,		0,		0,		0
		0,		200,	200,	200,	0,		100,	300,	200,	200,	300,	300,	200,	200,	300,	100,	0,		200,	200,	200,	0
		200,	200,	200,	200,	200,	200,	200,	200,	0,		0,		0,		0,		200,	200,	200,	200,	200,	200,	200,	200
		0,		200,	0,		200,	0,		200,	0,		300,	0,		-1,		-1,		0,		300,	0,		200,	0,		200,	0,		200,	0
		0,		200,	0,		200,	0,		200,	0,		300,	0,		-1,		-1,		0,		300,	0,		200,	0,		200,	0,		200,	0
		200,	200,	200,	200,	200,	200,	200,	200,	0,		0,		0,		0,		200,	200,	200,	200,	200,	200,	200,	200
		0,		200,	200,	200,	0,		100,	300,	200,	200,	300,	300,	200,	200,	300,	100,	0,		200,	200,	200,	0
		0,		0,		0,		0,		0,		100,	100,	300,	200,	0,		0,		200,	300,	100,	100,	0,		0,		0,		0,		0
		0,		0,		0,		0,		0,		0,		100,	100,	200,	200,	200,	200,	100,	100,	0,		0,		0,		0,		0,		0
		0,		0,		0,		0,		0,		0,		0,		0,		200,	0,		0,		200,	0,		0,		0,		0,		0,		0,		0,		0
		0,		0,		0,		0,		0,		0,		0,		0,		200,	200,	200,	200,	0,		0,		0,		0,		0,		0,		0,		0
		0,		0,		0,		0,		0,		0,		0,		0,		200,	0,		0,		200,	0,		0,		0,		0,		0,		0,		0,		0
		0,		0,		0,		0,		0,		0,		0,		0,		200,	200,	200,	200,	0,		0,		0,		0,		0,		0,		0,		0
		0,		0,		0,		0,		0,		0,		0,		0,		200,	0,		0,		200,	0,		0,		0,		0,		0,		0,		0,		0
	</design>
	<allowedVariables>100, 200, 300, 400</allowedVariables>
	<rotationMatrix>
		<rot0 x="0" z="0" />
		<rot1 x="0" z="0" />
		<rot2 x="0" z="0" />
		<rot3 x="0" z="0" />
	</rotationMatrix>
</rune>